cppio/__init__.py
cppio-1.0.dist-info/licenses/LICENSE
cppio-1.0.dist-info/METADATA
cppio-1.0.dist-info/WHEEL
cppio-1.0.dist-info/top_level.txt
cppio-1.0.dist-info/RECORD
